umbridge/__init__.py
umbridge/emcee.py
umbridge/pymc.py
umbridge/um.py
umbridge-1.2.4.dist-info/LICENSE
umbridge-1.2.4.dist-info/METADATA
umbridge-1.2.4.dist-info/WHEEL
umbridge-1.2.4.dist-info/top_level.txt
umbridge-1.2.4.dist-info/RECORD
