Metadata-Version: 2.1
Name: umbridge
Version: 1.2.4
Summary: UM-Bridge (the UQ and Model Bridge) provides a unified interface for numerical models that is accessible from virtually any programming language or framework. It is primarily intended for coupling advanced models (e.g. simulations of complex physical processes) to advanced statistical or optimization methods.
Home-page: https://github.com/UM-Bridge/umbridge
Author: UM-Bridge
Author-email: 
Classifier: Programming Language :: Python :: 3
Classifier: License :: OSI Approved :: MIT License
Classifier: Operating System :: OS Independent
License-File: LICENSE
Requires-Dist: aiohttp
Requires-Dist: requests
Requires-Dist: asyncio
